CHANGES.txt
LICENSE.txt
MANIFEST.in
README.txt
setup.py
js/__init__.py
js.responsiveiframe.egg-info/PKG-INFO
js.responsiveiframe.egg-info/SOURCES.txt
js.responsiveiframe.egg-info/dependency_links.txt
js.responsiveiframe.egg-info/entry_points.txt
js.responsiveiframe.egg-info/namespace_packages.txt
js.responsiveiframe.egg-info/not-zip-safe
js.responsiveiframe.egg-info/requires.txt
js.responsiveiframe.egg-info/top_level.txt
js/responsiveiframe/__init__.py
js/responsiveiframe/test_responsiveiframe.txt
js/responsiveiframe/resources/child_loader.js
js/responsiveiframe/resources/jquery.responsiveiframe.js