Metadata-Version: 1.0
Name: js.responsiveiframe
Version: 1.0
Summary: Fanstatic packaging of responsiveiframe
Home-page: UNKNOWN
Author: Fanstatic Developers
Author-email: fanstatic@googlegroups.com
License: BSD
Platform: UNKNOWN
